{
  "name": "VIRify",
  "url": "https://github.com/EBI-Metagenomics/emg-viral-pipeline",
  "provider": "github",
  "repo_path": "EBI-Metagenomics/emg-viral-pipeline",
  "description": "VIRify: detection of phages and eukaryotic viruses from metagenomic and metatranscriptomic assemblies",
  "created_at": "2020-04-29T16:04:00Z",
  "updated_at": "2025-03-11T06:12:54Z",
  "pushed_at": "2025-03-28T16:24:15Z",
  "stars": 131,
  "watchers": 131,
  "forks": 18,
  "open_issues": 22,
  "default_branch": "master",
  "license": "Apache License 2.0",
  "license_url": "https://api.github.com/licenses/apache-2.0",
  "homepage": "",
  "is_archived": false,
  "is_disabled": false,
  "fetch_time": "2025-04-01T08:40:01.576815",
  "languages": {
    "Python": 106383,
    "Nextflow": 75319,
    "Common Workflow Language": 70007,
    "Shell": 25425,
    "Dockerfile": 13555,
    "R": 7973,
    "Ruby": 6366
  },
  "topics": [
    "nextflow",
    "viruses",
    "cwl",
    "workflow",
    "pipeline"
  ],
  "latest_release": null,
  "dependencies": null
}